nonebot_plugin_sendpic/__init__.py
nonebot_plugin_sendpic/config.py
nonebot_plugin_sendpic-0.2.0.dist-info/LICENSE.txt
nonebot_plugin_sendpic-0.2.0.dist-info/METADATA
nonebot_plugin_sendpic-0.2.0.dist-info/WHEEL
nonebot_plugin_sendpic-0.2.0.dist-info/top_level.txt
nonebot_plugin_sendpic-0.2.0.dist-info/RECORD
