Metadata-Version: 2.1
Name: nonebot-plugin-sendpic
Version: 0.2.0
Summary: 基于图片api的nonebot发图插件，支持定时任务
Home-page: https://github.com/Funny1Potato/nonebot-plugin-sendpic
Author: Funny1Potato
Author-email: funny_potato@126.com
Classifier: Programming Language :: Python :: 3
Classifier: License :: OSI Approved :: MIT License
Classifier: Operating System :: OS Independent
Requires-Python: >=3.9
License-File: LICENSE.txt
Requires-Dist: nonebot2>=2.3
Requires-Dist: nonebot-plugin-apscheduler>=0.5
Requires-Dist: nonebot-adapter-onebot>=2.4
Requires-Dist: httpx>=0.27
